vitra/__init__.py
vitra-0.0.0.dist-info/METADATA
vitra-0.0.0.dist-info/WHEEL
vitra-0.0.0.dist-info/entry_points.txt
vitra-0.0.0.dist-info/top_level.txt
vitra-0.0.0.dist-info/RECORD
