Metadata-Version: 2.4
Name: Vitra
Version: 0.0.0
Summary: This package is reserved for the Vitra project. Updates will be available soon.
Author: Artur Arantes
License: MIT
Project-URL: Homepage, https://pypi.org/project/vitra/
Requires-Python: >=3.8
Requires-Dist: jinja2>=3.1
